xitkit/__init__.py
xitkit/__main__.py
xitkit/commands.py
xitkit/config.py
xitkit/dateutils.py
xitkit/description.py
xitkit/duedate.py
xitkit/exceptions.py
xitkit/file_repository.py
xitkit/fileparser.py
xitkit/formatter.py
xitkit/location.py
xitkit/patterns.py
xitkit/pomodoro.py
xitkit/priority.py
xitkit/services.py
xitkit/status.py
xitkit/tags.py
xitkit/task.py
xitkit-2.1.0.dist-info/METADATA
xitkit-2.1.0.dist-info/WHEEL
xitkit-2.1.0.dist-info/entry_points.txt
xitkit-2.1.0.dist-info/licenses/LICENSE
xitkit-2.1.0.dist-info/RECORD
