Metadata-Version: 2.4
Name: xitkit
Version: 2.1.0
Summary: A powerful command-line task management tool that parses and manages tasks from .xit and .md files using the x-it! format
License-Expression: MIT
License-File: LICENSE
Keywords: task,management,cli,todo,xit,productivity
Author: Christian
Author-email: 202550520+hoechstleistungshaartrockner@users.noreply.github.com
Requires-Python: >=3.14,<4.0.0
Classifier: Development Status :: 4 - Beta
Classifier: Intended Audience :: Developers
Classifier: Intended Audience :: End Users/Desktop
Classifier: License :: OSI Approved :: MIT License
Classifier: Programming Language :: Python :: 3
Classifier: Programming Language :: Python :: 3.14
Classifier: Topic :: Office/Business :: Scheduling
Classifier: Topic :: Utilities
Classifier: Environment :: Console
Provides-Extra: dev
Requires-Dist: black (>=23.0.0) ; extra == "dev"
Requires-Dist: click (>=8.0.0)
Requires-Dist: flake8 (>=6.0.0) ; extra == "dev"
Requires-Dist: isort (>=5.12.0) ; extra == "dev"
Requires-Dist: mypy (>=1.0.0) ; extra == "dev"
Requires-Dist: pytest (>=8.0.0) ; extra == "dev"
Requires-Dist: pytest-mock (>=3.10.0) ; extra == "dev"
Requires-Dist: pytest-xdist (>=3.0.0) ; extra == "dev"
Requires-Dist: questionary (>=2.1.1,<3.0.0)
Requires-Dist: rich (>=13.0.0)
Requires-Dist: textual (>=6.3.0,<7.0.0)
Project-URL: Bug Tracker, https://github.com/hoechstleistungshaartrockner/xitkit/issues
Project-URL: Homepage, https://github.com/hoechstleistungshaartrockner/xitkit
Project-URL: Repository, https://github.com/hoechstleistungshaartrockner/xitkit.git
